phyengine/DataEngine.py
phyengine/DynamicObjectManager.py
phyengine/InputManager.py
phyengine/MainEngine.py
phyengine/MathEngine.py
phyengine/TypesEngine.py
phyengine/__init__.py
phyengine-1.5.0.5.dist-info/METADATA
phyengine-1.5.0.5.dist-info/WHEEL
phyengine-1.5.0.5.dist-info/top_level.txt
phyengine-1.5.0.5.dist-info/RECORD
