Metadata-Version: 2.1
Name: phyengine
Version: 1.5.0.5
Summary: Pyhton library for simple physics modelation
Home-page: https://github.com/tacterex/PhyEngine
Author: tacterex
License: MIT
Classifier: Development Status :: 4 - Beta
Classifier: Programming Language :: Python
Requires-Dist: keyboard
Requires-Dist: openpyxl
